contentgrid_extension_helpers/__init__.py
contentgrid_extension_helpers/config.py
contentgrid_extension_helpers/exceptions.py
contentgrid_extension_helpers/problem_response.py
contentgrid_extension_helpers/authentication/__init__.py
contentgrid_extension_helpers/authentication/oidc.py
contentgrid_extension_helpers/authentication/user.py
contentgrid_extension_helpers/dependencies/authentication/user.py
contentgrid_extension_helpers/dependencies/clients/contentgrid/__init__.py
contentgrid_extension_helpers/dependencies/clients/contentgrid/client_factory.py
contentgrid_extension_helpers/dependencies/clients/contentgrid/extension_flow_factory.py
contentgrid_extension_helpers/dependencies/clients/contentgrid/service_account_factory.py
contentgrid_extension_helpers/dependencies/sqlalch/__init__.py
contentgrid_extension_helpers/dependencies/sqlalch/db/__init__.py
contentgrid_extension_helpers/dependencies/sqlalch/db/base_factory.py
contentgrid_extension_helpers/dependencies/sqlalch/db/postgres.py
contentgrid_extension_helpers/dependencies/sqlalch/db/sqlite.py
contentgrid_extension_helpers/dependencies/sqlalch/repositories/__init__.py
contentgrid_extension_helpers/dependencies/sqlalch/repositories/base_repository.py
contentgrid_extension_helpers/logging/__init__.py
contentgrid_extension_helpers/logging/json_logging.py
contentgrid_extension_helpers/middleware/exception_middleware.py
contentgrid_extension_helpers/responses/__init__.py
contentgrid_extension_helpers/responses/hal.py
contentgrid_extension_helpers/structured_output/model_deny.py
contentgrid_extension_helpers-0.0.3.dist-info/licenses/LICENSE
contentgrid_extension_helpers-0.0.3.dist-info/METADATA
contentgrid_extension_helpers-0.0.3.dist-info/WHEEL
contentgrid_extension_helpers-0.0.3.dist-info/top_level.txt
contentgrid_extension_helpers-0.0.3.dist-info/RECORD
