Metadata-Version: 2.4
Name: contentgrid-extension-helpers
Version: 0.0.3
Summary: Helper functions for contentgrid extensions.
Author-email: Ranec Belpaire <ranec.belpaire@xenit.eu>
License: Copyright 2024 Xenit Solutions
Classifier: Development Status :: 3 - Alpha
Classifier: Operating System :: OS Independent
Classifier: Programming Language :: Python :: 3
Requires-Python: >=3.5
License-File: LICENSE
Requires-Dist: requests<3,>=2.20.0
Requires-Dist: uri-template<2
Requires-Dist: fastapi>=0.111
Requires-Dist: PyJWT>2
Requires-Dist: cryptography>45
Requires-Dist: contentgrid_hal_client>=0.1
Requires-Dist: contentgrid_application_client>=0.1
Requires-Dist: contentgrid_management_client>=0.1
Requires-Dist: pydantic<3,>=2
Dynamic: license-file
